stora/__init__.py
stora/reactive.py
stora/storage.py
stora-0.0.3.dist-info/LICENSE
stora-0.0.3.dist-info/METADATA
stora-0.0.3.dist-info/WHEEL
stora-0.0.3.dist-info/top_level.txt
stora-0.0.3.dist-info/RECORD
