Metadata-Version: 2.1
Name: stora
Version: 0.0.3
Summary: A simple, reactive local storage library.
Home-page: https://github.com/louisyoungx/stora
Author: louisyoungx
Author-email: 1462648167@qq.com
License: UNKNOWN
Project-URL: Bug Tracker, https://github.com/louisyoungx/stora/issues
Platform: UNKNOWN
Classifier: Programming Language :: Python :: 3
Classifier: License :: OSI Approved :: MIT License
Classifier: Operating System :: OS Independent
Requires-Python: >=3.6
License-File: LICENSE
